soulseal/__init__.py
soulseal/__main__.py
soulseal/__version__.py
soulseal/endpoints.py
soulseal/examples/routes.py
soulseal/http.py
soulseal/schemas.py
soulseal/start.py
soulseal/tokens/__init__.py
soulseal/tokens/blacklist.py
soulseal/tokens/token_schemas.py
soulseal/tokens/token_sdk.py
soulseal/tokens/tokens_manager.py
soulseal/users/__init__.py
soulseal/users/user_schemas.py
soulseal/users/users.py
soulseal-0.1.13.dist-info/METADATA
soulseal-0.1.13.dist-info/WHEEL
soulseal-0.1.13.dist-info/entry_points.txt
soulseal-0.1.13.dist-info/RECORD
