Metadata-Version: 2.3
Name: soulseal
Version: 0.1.13
Summary: 这是一套适合Python快速开发的身份管理模块，SoulSeal 取自修仙小说中的「灵魂烙印」。
Author: arcstep
Author-email: 43801@qq.com
Requires-Python: >=3.11
Classifier: Programming Language :: Python :: 3
Classifier: Programming Language :: Python :: 3.11
Classifier: Programming Language :: Python :: 3.12
Classifier: Programming Language :: Python :: 3.13
Requires-Dist: aiohttp (>=3.11.16,<4.0.0)
Requires-Dist: argon2-cffi (>=23.1.0,<24.0.0)
Requires-Dist: async-timeout (>=5.0.1,<6.0.0)
Requires-Dist: email-validator (>=2.2.0,<3.0.0)
Requires-Dist: fastapi (>=0.115.9,<0.116.0)
Requires-Dist: httpx (>=0.28.1,<0.29.0)
Requires-Dist: pydantic (>=2.11.3,<3.0.0)
Requires-Dist: pyjwt (>=2.10.1,<3.0.0)
Requires-Dist: requests (>=2.32.3,<3.0.0)
Requires-Dist: responses (>=0.25.7,<0.26.0)
Requires-Dist: uvicorn (>=0.34.0,<0.35.0)
Requires-Dist: voidring (>=0.1.3,<0.2.0)
